notrition/__init__.py
notrition/notion.py
notrition/recipe.py
notrition-0.0.1.dist-info/METADATA
notrition-0.0.1.dist-info/WHEEL
notrition-0.0.1.dist-info/licenses/LICENSE
notrition-0.0.1.dist-info/RECORD
