Metadata-Version: 2.1
Name: notrition
Version: 0.0.1
Summary: Python script to save recipes directly to a Notion database.
Project-URL: Homepage, https://github.com/RobertDillon/notrition
Project-URL: Bug Tracker, https://github.com/RobertDillon/notrition/issues
Author-email: Robert Dillon <robdillon94@gmail.com>
License: MIT License
Classifier: License :: OSI Approved :: MIT License
Classifier: Operating System :: OS Independent
Classifier: Programming Language :: Python :: 3
Requires-Python: >=3.7
